MANIFEST.in
README.md
setup.cfg
setup.py
orionutils/__init__.py
orionutils/generator.py
orionutils/utils.py
orionutils.egg-info/PKG-INFO
orionutils.egg-info/SOURCES.txt
orionutils.egg-info/dependency_links.txt
orionutils.egg-info/requires.txt
orionutils.egg-info/top_level.txt
orionutils/collections/collection_dep_a/README.md
orionutils/collections/collection_dep_a/galaxy.yml
orionutils/collections/collection_dep_a1/README.md
orionutils/collections/collection_dep_a1/galaxy.yml
orionutils/collections/kitchensink/plugins/action/placeholder.py
orionutils/collections/kitchensink/plugins/callback/placeholder.py
orionutils/collections/kitchensink/plugins/filter/placeholder.py
orionutils/collections/kitchensink/plugins/inventory/placeholder.py
orionutils/collections/kitchensink/plugins/module_utils/placeholder.py
orionutils/collections/kitchensink/plugins/modules/placeholder.py
orionutils/collections/kitchensink/plugins/vars/placeholder.py
orionutils/collections/kitchensink/roles/placeholder/.gitignore
orionutils/collections/kitchensink/roles/placeholder/.travis.yml
orionutils/collections/kitchensink/roles/placeholder/LICENSE
orionutils/collections/kitchensink/roles/placeholder/README.md
orionutils/collections/kitchensink/roles/placeholder/defaults/main.yml
orionutils/collections/kitchensink/roles/placeholder/files/logstash.repo
orionutils/collections/kitchensink/roles/placeholder/files/filters/10-syslog.conf
orionutils/collections/kitchensink/roles/placeholder/files/filters/11-nginx.conf
orionutils/collections/kitchensink/roles/placeholder/files/filters/12-apache.conf
orionutils/collections/kitchensink/roles/placeholder/files/filters/14-solr.conf
orionutils/collections/kitchensink/roles/placeholder/files/filters/15-drupal.conf
orionutils/collections/kitchensink/roles/placeholder/handlers/main.yml
orionutils/collections/kitchensink/roles/placeholder/meta/main.yml
orionutils/collections/kitchensink/roles/placeholder/tasks/config.yml
orionutils/collections/kitchensink/roles/placeholder/tasks/main.yml
orionutils/collections/kitchensink/roles/placeholder/tasks/plugins.yml
